tinyticker/__init__.py
tinyticker/__main__.py
tinyticker/config.py
tinyticker/display.py
tinyticker/layouts/__init__.py
tinyticker/layouts/big_logo.py
tinyticker/layouts/big_price.py
tinyticker/layouts/default.py
tinyticker/layouts/register.py
tinyticker/layouts/utils.py
tinyticker/paths.py
tinyticker/sequence.py
tinyticker/socket.py
tinyticker/tickers/__init__.py
tinyticker/tickers/_base.py
tinyticker/tickers/crypto.py
tinyticker/tickers/stock.py
tinyticker/utils.py
tinyticker/waveshare_lib/__init__.py
tinyticker/waveshare_lib/_base.py
tinyticker/waveshare_lib/device.py
tinyticker/waveshare_lib/epd2in13.py
tinyticker/waveshare_lib/epd2in13_V2.py
tinyticker/waveshare_lib/epd2in13_V3.py
tinyticker/waveshare_lib/epd2in13_V4.py
tinyticker/waveshare_lib/epd2in13b_V3.py
tinyticker/waveshare_lib/epd2in13b_V4.py
tinyticker/waveshare_lib/epd2in13bc.py
tinyticker/waveshare_lib/epd2in7.py
tinyticker/waveshare_lib/epd2in7_V2.py
tinyticker/waveshare_lib/epd7in5b_V2.py
tinyticker/waveshare_lib/models.py
tinyticker/web/__init__.py
tinyticker/web/__main__.py
tinyticker/web/app.py
tinyticker/web/command.py
tinyticker/web/startup.py
tinyticker/web/templates/css/uikit.min.css
tinyticker/web/templates/images/apple-touch-icon.png
tinyticker/web/templates/images/favicon-16x16.png
tinyticker/web/templates/images/favicon-32x32.png
tinyticker/web/templates/index.html
tinyticker/web/templates/js/index.js
tinyticker/web/templates/js/uikit-icons.min.js
tinyticker/web/templates/js/uikit.min.js
tinyticker/web/templates/logfiles.html
tinyticker/web/templates/public/site.webmanifest
tinyticker/web/templates/startup.html
tinyticker-1.1.8.dist-info/LICENSE
tinyticker-1.1.8.dist-info/METADATA
tinyticker-1.1.8.dist-info/WHEEL
tinyticker-1.1.8.dist-info/entry_points.txt
tinyticker-1.1.8.dist-info/RECORD
