Metadata-Version: 2.1
Name: tinyticker
Version: 1.1.8
Summary: A tiny Raspberry Pi powered ePaper ticker.
Home-page: https://github.com/loiccoyle/tinyticker
License: MIT
Keywords: raspberry-pi,ticker,stock,crypto,epaper,finance
Author: Loic Coyle
Author-email: loic.coyle@hotmail.fr
Requires-Python: >=3.10
Classifier: License :: OSI Approved :: MIT License
Classifier: Programming Language :: Python :: 3
Classifier: Programming Language :: Python :: 3.10
Classifier: Programming Language :: Python :: 3.11
Classifier: Programming Language :: Python :: 3.12
Requires-Dist: Flask (>=3.0.0,<4.0.0)
Requires-Dist: Pillow (>=10.0.1,<11.0.0)
Requires-Dist: cryptocompare (>=0.7.5,<0.8.0)
Requires-Dist: gpiozero (>=2.0.1,<3.0.0)
Requires-Dist: matplotlib (>=3.5.1,<4.0.0)
Requires-Dist: mplfinance (>=0.12.7-alpha.17,<0.13.0)
Requires-Dist: numpy (>=2.2.1,<3.0.0)
Requires-Dist: packaging (>=23.0,<24.0)
Requires-Dist: pandas (>=2.2.3,<3.0.0)
Requires-Dist: qrcode (>=7.3.1,<8.0.0)
Requires-Dist: spidev (>=3.5,<4.0)
Requires-Dist: waitress (>=3.0.0,<4.0.0)
Requires-Dist: watchdog (>=4.0.0,<5.0.0)
Requires-Dist: yfinance (>=0.2.54,<0.3.0)
Project-URL: Repository, https://github.com/loiccoyle/tinyticker
